nested_json2rel_data/__init__.py
nested_json2rel_data/nested_json_parser.py
nested_json2rel_data-0.0.2.dist-info/LICENSE
nested_json2rel_data-0.0.2.dist-info/METADATA
nested_json2rel_data-0.0.2.dist-info/WHEEL
nested_json2rel_data-0.0.2.dist-info/top_level.txt
nested_json2rel_data-0.0.2.dist-info/RECORD
