Metadata-Version: 2.1
Name: nested-json2rel-data
Version: 0.0.2
Summary: package to convert nested json to relational and flat data structure.  
Home-page: UNKNOWN
Author: Joy Maitra
Author-email: joy_maitra@yahoo.co.in
License: UNKNOWN
Platform: UNKNOWN
Classifier: Programming Language :: Python :: 3
Classifier: License :: OSI Approved :: MIT License
Classifier: Operating System :: OS Independent
Requires-Python: >=3.6
